c4t/__init__.py
c4t/cli.py
c4t-1.6.0.dist-info/LICENSE
c4t-1.6.0.dist-info/METADATA
c4t-1.6.0.dist-info/WHEEL
c4t-1.6.0.dist-info/entry_points.txt
c4t-1.6.0.dist-info/top_level.txt
c4t-1.6.0.dist-info/RECORD
