Metadata-Version: 2.1
Name: c4t
Version: 1.6.0
Summary: Install Chrome for Testing assets.
Author-email: p4irin <139928764+p4irin@users.noreply.github.com>
Project-URL: Homepage, https://github.com/p4irin/c4t
Project-URL: Bug Tracker, https://github.com/p4irin/c4t/issues
Keywords: chrome,testing,selenium,chromedriver,cft
Classifier: Programming Language :: Python :: 3
Classifier: Programming Language :: Python :: 3.8
Classifier: Programming Language :: Python :: 3.9
Classifier: Programming Language :: Python :: 3.10
Classifier: Operating System :: POSIX :: Linux
Classifier: Intended Audience :: Developers
Classifier: Topic :: Software Development :: Libraries :: Python Modules
Classifier: Topic :: Software Development :: Quality Assurance
Classifier: Topic :: Software Development :: Testing
Classifier: License :: OSI Approved :: MIT License
Requires-Python: >=3.8.10
License-File: LICENSE
Requires-Dist: requests >=2.31.0
Requires-Dist: wget >=3.2
Provides-Extra: dev
Requires-Dist: bumpver >=2023.1126 ; extra == 'dev'
Requires-Dist: c4t[lint] ; extra == 'dev'
Requires-Dist: c4t[test] ; extra == 'dev'
Requires-Dist: c4t[package] ; extra == 'dev'
Provides-Extra: lint
Requires-Dist: mypy >=1.9.0 ; extra == 'lint'
Requires-Dist: types-requests >=2.31.0.20240311 ; extra == 'lint'
Requires-Dist: ruff >=0.3.4 ; extra == 'lint'
Provides-Extra: package
Requires-Dist: build ==0.10.0 ; extra == 'package'
Requires-Dist: twine >=4.0.2 ; extra == 'package'
Provides-Extra: test
Requires-Dist: selenium >=4.12.0 ; extra == 'test'
Requires-Dist: pytest >=8.1.1 ; extra == 'test'
Requires-Dist: pytest-cov >=4.1.0 ; extra == 'test'
